nbmake/nb_result.py
nbmake/nb_run.py
nbmake/pytest_items.py
nbmake/pytest_plugin.py
nbmake-1.5.4.dist-info/LICENSE
nbmake-1.5.4.dist-info/METADATA
nbmake-1.5.4.dist-info/WHEEL
nbmake-1.5.4.dist-info/entry_points.txt
nbmake-1.5.4.dist-info/RECORD
