Metadata-Version: 2.1
Name: nbmake
Version: 1.5.4
Summary: Pytest plugin for testing notebooks
Home-page: https://github.com/treebeardtech/nbmake
License: Apache-2.0
Author: alex-treebeard
Author-email: alex@treebeard.io
Requires-Python: >=3.8.0,<4.0.0
Classifier: License :: OSI Approved :: Apache Software License
Classifier: Programming Language :: Python :: 3
Classifier: Programming Language :: Python :: 3.8
Classifier: Programming Language :: Python :: 3.9
Classifier: Programming Language :: Python :: 3.10
Classifier: Programming Language :: Python :: 3.11
Classifier: Programming Language :: Python :: 3.12
Requires-Dist: Pygments (>=2.7.3,<3.0.0)
Requires-Dist: ipykernel (>=5.4.0)
Requires-Dist: nbclient (>=0.6.6,<0.7.0)
Requires-Dist: nbformat (>=5.0.8,<6.0.0)
Requires-Dist: pytest (>=6.1.0)
